archey/__init__.py
archey/__main__.py
archey/_version.py
archey/api.py
archey/colors.py
archey/configuration.py
archey/distributions.py
archey/entry.py
archey/environment.py
archey/exceptions.py
archey/output.py
archey/processes.py
archey/py.typed
archey/screenshot.py
archey/singleton.py
archey/utility.py
archey/entries/__init__.py
archey/entries/cpu.py
archey/entries/custom.py
archey/entries/desktop_environment.py
archey/entries/disk.py
archey/entries/distro.py
archey/entries/gpu.py
archey/entries/hostname.py
archey/entries/kernel.py
archey/entries/lan_ip.py
archey/entries/load_average.py
archey/entries/model.py
archey/entries/packages.py
archey/entries/processes.py
archey/entries/ram.py
archey/entries/shell.py
archey/entries/temperature.py
archey/entries/terminal.py
archey/entries/uptime.py
archey/entries/user.py
archey/entries/wan_ip.py
archey/entries/window_manager.py
archey/logos/__init__.py
archey/logos/alpine.py
archey/logos/android.py
archey/logos/arch.py
archey/logos/armbian.py
archey/logos/buildroot.py
archey/logos/bunsenlabs.py
archey/logos/centos.py
archey/logos/crunchbang.py
archey/logos/darwin.py
archey/logos/debian.py
archey/logos/devuan.py
archey/logos/elementary.py
archey/logos/endeavouros.py
archey/logos/enso.py
archey/logos/fedora.py
archey/logos/freebsd.py
archey/logos/gentoo.py
archey/logos/guix.py
archey/logos/kali.py
archey/logos/linux.py
archey/logos/linuxmint.py
archey/logos/manjaro.py
archey/logos/moevalent.py
archey/logos/netbsd.py
archey/logos/nixos.py
archey/logos/nobara.py
archey/logos/openbsd.py
archey/logos/opensuse.py
archey/logos/parabola.py
archey/logos/pop.py
archey/logos/quirinux.py
archey/logos/raspbian.py
archey/logos/rhel.py
archey/logos/rocky.py
archey/logos/siduction.py
archey/logos/slackware.py
archey/logos/ubuntu.py
archey/logos/univalent.py
archey/logos/windows.py
archey4-4.15.0.0.data/data/share/doc/archey4/CHANGELOG.md
archey4-4.15.0.0.data/data/share/doc/archey4/COPYRIGHT.md
archey4-4.15.0.0.dist-info/LICENSE
archey4-4.15.0.0.dist-info/METADATA
archey4-4.15.0.0.dist-info/WHEEL
archey4-4.15.0.0.dist-info/entry_points.txt
archey4-4.15.0.0.dist-info/top_level.txt
archey4-4.15.0.0.dist-info/RECORD
