Metadata-Version: 2.1
Name: archey4
Version: 4.15.0.0
Summary: Archey is a simple system information tool written in Python
Home-page: https://github.com/HorlogeSkynet/archey4
Author: Samuel Forestier
Author-email: samuel+archey@forestier.app
License: GPLv3
Keywords: archey python3 linux system-information monitoring screenshot
Platform: UNKNOWN
Classifier: Development Status :: 5 - Production/Stable
Classifier: Environment :: Console
Classifier: Intended Audience :: Developers
Classifier: Intended Audience :: Information Technology
Classifier: Intended Audience :: System Administrators
Classifier: License :: OSI Approved :: GNU General Public License v3 (GPLv3)
Classifier: Natural Language :: English
Classifier: Operating System :: Android
Classifier: Operating System :: MacOS
Classifier: Operating System :: POSIX :: BSD
Classifier: Operating System :: POSIX :: Linux
Classifier: Programming Language :: Python :: 3
Classifier: Programming Language :: Python :: 3.6
Classifier: Programming Language :: Python :: 3.7
Classifier: Programming Language :: Python :: 3.8
Classifier: Programming Language :: Python :: 3.9
Classifier: Programming Language :: Python :: 3.10
Classifier: Programming Language :: Python :: 3.11
Classifier: Programming Language :: Python :: 3.12
Classifier: Programming Language :: Python :: 3 :: Only
Classifier: Topic :: System
Requires-Python: >=3.6
Requires-Dist: distro ~=1.3
Requires-Dist: netifaces ~=0.10
